regime/__init__.py
regime/utils.py
regime/flow/__init__.py
regime/flow/components.py
regime/flow/impl.py
regime/flow/threads.py
regime/nodes/__init__.py
regime/nodes/decorators.py
regime/nodes/impl.py
regime/nodes/meta.py
regime-0.0.4.dist-info/METADATA
regime-0.0.4.dist-info/WHEEL
regime-0.0.4.dist-info/licenses/LICENSE
regime-0.0.4.dist-info/RECORD
