Metadata-Version: 2.3
Name: regime
Version: 0.0.4
Summary: Create and visualize workflows consisting of classes, functions, and resources; recognize hyperparameters when needed.
Project-URL: Homepage, https://github.com/johnHostetter/regime
Project-URL: Issues, https://github.com/johnHostetter/regime/issues
Author-email: John Wesley Hostetter <jhostetter16@gmail.com>
License-File: LICENSE
Classifier: License :: OSI Approved :: MIT License
Classifier: Operating System :: OS Independent
Classifier: Programming Language :: Python :: 3
Requires-Python: >=3.9
